<?xml version="1.0" encoding="encoding"?>
<list>
  <RegU>
    <age>34</age>
    <avataring>/home/osotemi/NetBeansProjects/Framework_v1.6.3/src/framework/img/profile_pictures/people-18.png</avataring>
    <born__date>
      <milsec>0</milsec>
      <second>0</second>
      <minute>0</minute>
      <hour>0</hour>
      <day>13</day>
      <month>3</month>
      <year>1982</year>
      <sdate>13/03/1982</sdate>
    </born__date>
    <dni>36720207-V</dni>
    <email>xorx.millan@gmail.com</email>
    <movile>662201483</movile>
    <name>Xorx</name>
    <lastname>Millán Puente</lastname>
    <password>9EuNLvLt</password>
    <state>Offline</state>
    <user>XorMil</user>
    <benefit>4275.0</benefit>
    <activity>2850</activity>
    <karma>high</karma>
  </RegU>
  <RegU>
    <age>34</age>
    <avataring>/home/osotemi/NetBeansProjects/Framework_v1.6.3/src/framework/img/profile_pictures/people-13.png</avataring>
    <born__date>
      <milsec>0</milsec>
      <second>0</second>
      <minute>0</minute>
      <hour>0</hour>
      <day>3</day>
      <month>6</month>
      <year>1981</year>
      <sdate>03/06/1981</sdate>
    </born__date>
    <dni>11687419-S</dni>
    <email>joan.serrano@omail.com</email>
    <movile>600227004</movile>
    <name>Joan</name>
    <lastname>Serrano Sanz</lastname>
    <password>BS9ncadOPvb</password>
    <state>Online</state>
    <user>JoaSer</user>
    <benefit>5724.0</benefit>
    <activity>3816</activity>
    <karma>high</karma>
  </RegU>
  <RegU>
    <age>44</age>
    <avataring>/home/osotemi/NetBeansProjects/Framework_v1.6.3/src/framework/img/profile_pictures/people-19.png</avataring>
    <born__date>
      <milsec>0</milsec>
      <second>0</second>
      <minute>0</minute>
      <hour>0</hour>
      <day>15</day>
      <month>5</month>
      <year>1971</year>
      <sdate>15/05/1971</sdate>
    </born__date>
    <dni>18089570-R</dni>
    <email>pepe.mercado@gmail.com</email>
    <movile>672001953</movile>
    <name>Pepe</name>
    <lastname>Mercado Paz</lastname>
    <password>mK16B5dtFL2ruN</password>
    <state>Logged</state>
    <user>PepMer</user>
    <benefit>10882.5</benefit>
    <activity>7255</activity>
    <karma>high</karma>
  </RegU>
  <RegU>
    <age>30</age>
    <avataring>e1206k6ik9rO137E</avataring>
    <born__date>
      <milsec>0</milsec>
      <second>0</second>
      <minute>0</minute>
      <hour>0</hour>
      <day>24</day>
      <month>8</month>
      <year>1985</year>
      <sdate>24/08/1985</sdate>
    </born__date>
    <dni>82831273-Q</dni>
    <email>uxia.de@gmail.com</email>
    <movile>666351967</movile>
    <name>Uxia</name>
    <lastname>De Castro Callaú</lastname>
    <password></password>
    <state>Offline</state>
    <user>UxiDeva</user>
    <benefit>1000.5</benefit>
    <activity>667</activity>
    <karma>high</karma>
  </RegU>
  <RegU>
    <age>19</age>
    <avataring>/home/osotemi/NetBeansProjects/Framework_v1.6.3/src/framework/img/profile_pictures/people-6.png</avataring>
    <born__date>
      <milsec>0</milsec>
      <second>0</second>
      <minute>0</minute>
      <hour>0</hour>
      <day>15</day>
      <month>7</month>
      <year>1996</year>
      <sdate>15/07/1996</sdate>
    </born__date>
    <dni>64117068-Z</dni>
    <email>emilia.ramone@gmail.com</email>
    <movile>663863981</movile>
    <name>Emilia</name>
    <lastname>Ramone Callaú</lastname>
    <password>BE91NkoibHf35F8</password>
    <state>Online</state>
    <user>EmiRam</user>
    <benefit>1489.5</benefit>
    <activity>993</activity>
    <karma>high</karma>
  </RegU>
  <RegU>
    <age>36</age>
    <avataring>/home/osotemi/NetBeansProjects/Framework_v1.6.3/src/framework/img/profile_pictures/people-22.png</avataring>
    <born__date>
      <milsec>0</milsec>
      <second>0</second>
      <minute>0</minute>
      <hour>0</hour>
      <day>4</day>
      <month>6</month>
      <year>1979</year>
      <sdate>04/06/1979</sdate>
    </born__date>
    <dni>85876067-R</dni>
    <email>sonia.millan@omail.com</email>
    <movile>650673080</movile>
    <name>Sonia</name>
    <lastname>Millán Otero</lastname>
    <password>eF8f1DlL9j</password>
    <state>Logged</state>
    <user>SonMil</user>
    <benefit>2995.5</benefit>
    <activity>1997</activity>
    <karma>high</karma>
  </RegU>
  <RegU>
    <age>27</age>
    <avataring>/home/osotemi/NetBeansProjects/Framework_v1.6.3/src/framework/img/profile_pictures/people-21.png</avataring>
    <born__date>
      <milsec>0</milsec>
      <second>0</second>
      <minute>0</minute>
      <hour>0</hour>
      <day>4</day>
      <month>3</month>
      <year>1989</year>
      <sdate>04/03/1989</sdate>
    </born__date>
    <dni>67537872-M</dni>
    <email>juanjo.teruel@omail.com</email>
    <movile>642960330</movile>
    <name>Juanjo</name>
    <lastname>Teruel Otero</lastname>
    <password>4Z3kn7lvi6B</password>
    <state>Offline</state>
    <user>JuaTer</user>
    <benefit>231.0</benefit>
    <activity>154</activity>
    <karma>high</karma>
  </RegU>
  <RegU>
    <age>43</age>
    <avataring>/home/osotemi/NetBeansProjects/Framework_v1.6.3/src/framework/img/profile_pictures/people-6.png</avataring>
    <born__date>
      <milsec>0</milsec>
      <second>0</second>
      <minute>0</minute>
      <hour>0</hour>
      <day>1</day>
      <month>2</month>
      <year>1973</year>
      <sdate>01/02/1973</sdate>
    </born__date>
    <dni>24677548-C</dni>
    <email>roser.sanz@gmail.com</email>
    <movile>600585814</movile>
    <name>Roser</name>
    <lastname>Sanz Martínez</lastname>
    <password>kgjZ23p75BVH</password>
    <state>Online</state>
    <user>RosSan</user>
    <benefit>8485.5</benefit>
    <activity>5657</activity>
    <karma>high</karma>
  </RegU>
  <RegU>
    <age>64</age>
    <avataring>/home/osotemi/NetBeansProjects/Framework_v1.6.3/src/framework/img/profile_pictures/people-18.png</avataring>
    <born__date>
      <milsec>0</milsec>
      <second>0</second>
      <minute>0</minute>
      <hour>0</hour>
      <day>19</day>
      <month>1</month>
      <year>1952</year>
      <sdate>19/01/1952</sdate>
    </born__date>
    <dni>71635084-C</dni>
    <email>uxia.mercado@gmail.com</email>
    <movile>639613457</movile>
    <name>Uxia</name>
    <lastname>Mercado Martínez</lastname>
    <password>0pikNw87sRK19dGw</password>
    <state>Offline</state>
    <user>UxiMer</user>
    <benefit>25510.5</benefit>
    <activity>17007</activity>
    <karma>high</karma>
  </RegU>
  <RegU>
    <age>64</age>
    <avataring>/home/osotemi/NetBeansProjects/Framework_v1.6.3/src/framework/img/profile_pictures/people-18.png</avataring>
    <born__date>
      <milsec>0</milsec>
      <second>0</second>
      <minute>0</minute>
      <hour>0</hour>
      <day>22</day>
      <month>1</month>
      <year>1952</year>
      <sdate>22/01/1952</sdate>
    </born__date>
    <dni>85603409-P</dni>
    <email>michael.martinez@gmail.com</email>
    <movile>698959737</movile>
    <name>Michael</name>
    <lastname>Martínez Otero</lastname>
    <password>jw7r74CkuSk</password>
    <state>Logged</state>
    <user>MicMar</user>
    <benefit>10923.0</benefit>
    <activity>7282</activity>
    <karma>high</karma>
  </RegU>
  <RegU>
    <age>19</age>
    <avataring>/home/osotemi/NetBeansProjects/Framework_v1.6.3/src/framework/img/profile_pictures/people-2.png</avataring>
    <born__date>
      <milsec>0</milsec>
      <second>0</second>
      <minute>0</minute>
      <hour>0</hour>
      <day>24</day>
      <month>11</month>
      <year>1996</year>
      <sdate>24/11/1996</sdate>
    </born__date>
    <dni>58382300-C</dni>
    <email>elena.de@omail.com</email>
    <movile>627001024</movile>
    <name>Elena</name>
    <lastname>De Castro Zorrilla</lastname>
    <password>7we788O74</password>
    <state>Online</state>
    <user>EleDe </user>
    <benefit>625.5</benefit>
    <activity>417</activity>
    <karma>high</karma>
  </RegU>
  <RegU>
    <age>26</age>
    <avataring>/home/osotemi/NetBeansProjects/Framework_v1.6.3/src/framework/img/profile_pictures/people-26.png</avataring>
    <born__date>
      <milsec>0</milsec>
      <second>0</second>
      <minute>0</minute>
      <hour>0</hour>
      <day>23</day>
      <month>10</month>
      <year>1989</year>
      <sdate>23/10/1989</sdate>
    </born__date>
    <dni>16765154-V</dni>
    <email>joan.marin@omail.com</email>
    <movile>625506518</movile>
    <name>Joan</name>
    <lastname>Marín Serrano</lastname>
    <password>gTawujvmT</password>
    <state>Logged</state>
    <user>JoaMar</user>
    <benefit>6966.0</benefit>
    <activity>4644</activity>
    <karma>high</karma>
  </RegU>
  <RegU>
    <age>40</age>
    <avataring>2R79TK90WnK3</avataring>
    <born__date>
      <milsec>0</milsec>
      <second>0</second>
      <minute>0</minute>
      <hour>0</hour>
      <day>5</day>
      <month>3</month>
      <year>1976</year>
      <sdate>05/03/1976</sdate>
    </born__date>
    <dni>60824523-B</dni>
    <email>alfons.millan@gmail.com</email>
    <movile>605073233</movile>
    <name>Alfons</name>
    <lastname>Millán Teruel</lastname>
    <password></password>
    <state>Online</state>
    <user>AlfMil</user>
    <benefit>14020.5</benefit>
    <activity>9347</activity>
    <karma>high</karma>
  </RegU>
  <RegU>
    <age>38</age>
    <avataring>oM0b3F57M2oEw1</avataring>
    <born__date>
      <milsec>0</milsec>
      <second>0</second>
      <minute>0</minute>
      <hour>0</hour>
      <day>18</day>
      <month>10</month>
      <year>1977</year>
      <sdate>18/10/1977</sdate>
    </born__date>
    <dni>89195693-Z</dni>
    <email>joey.rebate@gmail.com</email>
    <movile>601881157</movile>
    <name>Joey</name>
    <lastname>Rebate Martínez</lastname>
    <password></password>
    <state>Online</state>
    <user>JoeReb</user>
    <benefit>1107.0</benefit>
    <activity>738</activity>
    <karma>high</karma>
  </RegU>
  <RegU>
    <age>25</age>
    <avataring>/home/osotemi/NetBeansProjects/Framework_v1.6.3/src/framework/img/profile_pictures/people-16.png</avataring>
    <born__date>
      <milsec>0</milsec>
      <second>0</second>
      <minute>0</minute>
      <hour>0</hour>
      <day>26</day>
      <month>3</month>
      <year>1991</year>
      <sdate>26/03/1991</sdate>
    </born__date>
    <dni>32704251-E</dni>
    <email>alba.zorrilla@gmail.com</email>
    <movile>678850217</movile>
    <name>Alba</name>
    <lastname>Zorrilla Beltrán</lastname>
    <password>31VG9u0a</password>
    <state>Online</state>
    <user>AlbZor</user>
    <benefit>1143.0</benefit>
    <activity>762</activity>
    <karma>high</karma>
  </RegU>
  <RegU>
    <age>57</age>
    <avataring>/home/osotemi/NetBeansProjects/Framework_v1.6.3/src/framework/img/profile_pictures/people-13.png</avataring>
    <born__date>
      <milsec>0</milsec>
      <second>0</second>
      <minute>0</minute>
      <hour>0</hour>
      <day>11</day>
      <month>6</month>
      <year>1958</year>
      <sdate>11/06/1958</sdate>
    </born__date>
    <dni>22574709-W</dni>
    <email>sara.gaya@omail.com</email>
    <movile>699864056</movile>
    <name>Sara</name>
    <lastname>Gayá Márquez</lastname>
    <password>JaVz352758o1ehdR</password>
    <state>Offline</state>
    <user>SarGay</user>
    <benefit>2544.0</benefit>
    <activity>1696</activity>
    <karma>high</karma>
  </RegU>
  <RegU>
    <age>59</age>
    <avataring>/home/osotemi/NetBeansProjects/Framework_v1.6.3/src/framework/img/profile_pictures/people-10.png</avataring>
    <born__date>
      <milsec>0</milsec>
      <second>0</second>
      <minute>0</minute>
      <hour>0</hour>
      <day>4</day>
      <month>2</month>
      <year>1957</year>
      <sdate>04/02/1957</sdate>
    </born__date>
    <dni>87113247-B</dni>
    <email>damian.cobain@gmail.com</email>
    <movile>618853784</movile>
    <name>Damián</name>
    <lastname>Cobain Buenafuente</lastname>
    <password>2Fpkw80also5B</password>
    <state>Online</state>
    <user>DamCob</user>
    <benefit>1570.5</benefit>
    <activity>1047</activity>
    <karma>high</karma>
  </RegU>
  <RegU>
    <age>49</age>
    <avataring>/home/osotemi/NetBeansProjects/Framework_v1.6.3/src/framework/img/profile_pictures/people-8.png</avataring>
    <born__date>
      <milsec>0</milsec>
      <second>0</second>
      <minute>0</minute>
      <hour>0</hour>
      <day>26</day>
      <month>5</month>
      <year>1966</year>
      <sdate>26/05/1966</sdate>
    </born__date>
    <dni>75015522-X</dni>
    <email>pep.de@gmail.com</email>
    <movile>603612318</movile>
    <name>Pep</name>
    <lastname>De Las Mulas Millán</lastname>
    <password>P7IpEwAPn</password>
    <state>Offline</state>
    <user>PepDe </user>
    <benefit>4888.5</benefit>
    <activity>3259</activity>
    <karma>high</karma>
  </RegU>
  <RegU>
    <age>32</age>
    <avataring>/home/osotemi/NetBeansProjects/Framework_v1.6.3/src/framework/img/profile_pictures/people-22.png</avataring>
    <born__date>
      <milsec>0</milsec>
      <second>0</second>
      <minute>0</minute>
      <hour>0</hour>
      <day>26</day>
      <month>3</month>
      <year>1984</year>
      <sdate>26/03/1984</sdate>
    </born__date>
    <dni>56204143-D</dni>
    <email>elena.pages@gmail.com</email>
    <movile>613483299</movile>
    <name>Elena</name>
    <lastname>Pagés Giadas</lastname>
    <password>1Oz6186nka</password>
    <state>Online</state>
    <user>ElePag</user>
    <benefit>2091.0</benefit>
    <activity>1394</activity>
    <karma>high</karma>
  </RegU>
  <RegU>
    <age>55</age>
    <avataring>/home/osotemi/NetBeansProjects/Framework_v1.6.3/src/framework/img/profile_pictures/people-19.png</avataring>
    <born__date>
      <milsec>0</milsec>
      <second>0</second>
      <minute>0</minute>
      <hour>0</hour>
      <day>19</day>
      <month>8</month>
      <year>1960</year>
      <sdate>19/08/1960</sdate>
    </born__date>
    <dni>99718444-N</dni>
    <email>daniel.pavia@gmail.com</email>
    <movile>621437465</movile>
    <name>Daniel</name>
    <lastname>Pavía Martínez</lastname>
    <password>2h4gd1wjz1a93</password>
    <state>Logged</state>
    <user>DanPav</user>
    <benefit>5524.5</benefit>
    <activity>3683</activity>
    <karma>high</karma>
  </RegU>
  <RegU>
    <age>20</age>
    <avataring>/home/osotemi/NetBeansProjects/Framework_v1.6.3/src/framework/img/profile_pictures/people-21.png</avataring>
    <born__date>
      <milsec>0</milsec>
      <second>0</second>
      <minute>0</minute>
      <hour>0</hour>
      <day>14</day>
      <month>2</month>
      <year>1996</year>
      <sdate>14/02/1996</sdate>
    </born__date>
    <dni>48910798-X</dni>
    <email>lola.ramone@omail.com</email>
    <movile>681660285</movile>
    <name>Lola</name>
    <lastname>Ramone Puente</lastname>
    <password>94SJ1lGe62nNKu</password>
    <state>Logged</state>
    <user>LolRam</user>
    <benefit>298.5</benefit>
    <activity>199</activity>
    <karma>high</karma>
  </RegU>
  <RegU>
    <age>60</age>
    <avataring>/home/osotemi/NetBeansProjects/Framework_v1.6.3/src/framework/img/profile_pictures/people-7.png</avataring>
    <born__date>
      <milsec>0</milsec>
      <second>0</second>
      <minute>0</minute>
      <hour>0</hour>
      <day>21</day>
      <month>10</month>
      <year>1955</year>
      <sdate>21/10/1955</sdate>
    </born__date>
    <dni>19728155-C</dni>
    <email>juanjo.salvador@gmail.com</email>
    <movile>628942002</movile>
    <name>Juanjo</name>
    <lastname>Salvador Plaza</lastname>
    <password>0HLE0pUwt</password>
    <state>Logged</state>
    <user>JuaSal</user>
    <benefit>21462.0</benefit>
    <activity>14308</activity>
    <karma>high</karma>
  </RegU>
  <RegU>
    <age>62</age>
    <avataring>/home/osotemi/NetBeansProjects/Framework_v1.6.3/src/framework/img/profile_pictures/people-23.png</avataring>
    <born__date>
      <milsec>0</milsec>
      <second>0</second>
      <minute>0</minute>
      <hour>0</hour>
      <day>5</day>
      <month>1</month>
      <year>1954</year>
      <sdate>05/01/1954</sdate>
    </born__date>
    <dni>26897174-P</dni>
    <email>marc.marquez@omail.com</email>
    <movile>656306133</movile>
    <name>Marc</name>
    <lastname>Márquez Mercado</lastname>
    <password>2bTH968LIkvv</password>
    <state>Offline</state>
    <user>MarMár</user>
    <benefit>8334.0</benefit>
    <activity>5556</activity>
    <karma>high</karma>
  </RegU>
  <RegU>
    <age>35</age>
    <avataring>/home/osotemi/NetBeansProjects/Framework_v1.6.3/src/framework/img/profile_pictures/people-22.png</avataring>
    <born__date>
      <milsec>0</milsec>
      <second>0</second>
      <minute>0</minute>
      <hour>0</hour>
      <day>17</day>
      <month>9</month>
      <year>1980</year>
      <sdate>17/09/1980</sdate>
    </born__date>
    <dni>84260867-E</dni>
    <email>araceli.rodriguez@omail.com</email>
    <movile>684517924</movile>
    <name>Araceli</name>
    <lastname>Rodríguez Mercado</lastname>
    <password>FBLCSbO66AIZb</password>
    <state>Logged</state>
    <user>AraRod</user>
    <benefit>5382.0</benefit>
    <activity>3588</activity>
    <karma>high</karma>
  </RegU>
  <RegU>
    <age>23</age>
    <avataring>/home/osotemi/NetBeansProjects/Framework_v1.6.3/src/framework/img/profile_pictures/people-2.png</avataring>
    <born__date>
      <milsec>0</milsec>
      <second>0</second>
      <minute>0</minute>
      <hour>0</hour>
      <day>14</day>
      <month>9</month>
      <year>1992</year>
      <sdate>14/09/1992</sdate>
    </born__date>
    <dni>25719770-C</dni>
    <email>joan.navarro@gmail.com</email>
    <movile>680447073</movile>
    <name>Joan</name>
    <lastname>Navarro Plaza</lastname>
    <password>C081Nd5j6</password>
    <state>Logged</state>
    <user>JoaNav</user>
    <benefit>2829.0</benefit>
    <activity>1886</activity>
    <karma>high</karma>
  </RegU>
  <RegU>
    <age>20</age>
    <avataring>/home/osotemi/NetBeansProjects/Framework_v1.6.3/src/framework/img/profile_pictures/people-2.png</avataring>
    <born__date>
      <milsec>0</milsec>
      <second>0</second>
      <minute>0</minute>
      <hour>0</hour>
      <day>28</day>
      <month>4</month>
      <year>1995</year>
      <sdate>28/04/1995</sdate>
    </born__date>
    <dni>28087359-N</dni>
    <email>jorge.beltran@gmail.com</email>
    <movile>674143578</movile>
    <name>Jorge</name>
    <lastname>Beltrán Gayá</lastname>
    <password>demFs662c8bmR6j3</password>
    <state>Offline</state>
    <user>JorBel</user>
    <benefit>2629.5</benefit>
    <activity>1753</activity>
    <karma>high</karma>
  </RegU>
  <RegU>
    <age>41</age>
    <avataring>/home/osotemi/NetBeansProjects/Framework_v1.6.3/src/framework/img/profile_pictures/people-5.png</avataring>
    <born__date>
      <milsec>0</milsec>
      <second>0</second>
      <minute>0</minute>
      <hour>0</hour>
      <day>12</day>
      <month>10</month>
      <year>1974</year>
      <sdate>12/10/1974</sdate>
    </born__date>
    <dni>34860700-Z</dni>
    <email>jorge.de@omail.com</email>
    <movile>664745437</movile>
    <name>Jorge</name>
    <lastname>De Las Mulas Gayá</lastname>
    <password>sk8OkEjKb5G</password>
    <state>Offline</state>
    <user>JorDe </user>
    <benefit>681.0</benefit>
    <activity>454</activity>
    <karma>high</karma>
  </RegU>
  <RegU>
    <age>55</age>
    <avataring>/home/osotemi/NetBeansProjects/Framework_v1.6.3/src/framework/img/profile_pictures/people-12.png</avataring>
    <born__date>
      <milsec>0</milsec>
      <second>0</second>
      <minute>0</minute>
      <hour>0</hour>
      <day>12</day>
      <month>8</month>
      <year>1960</year>
      <sdate>12/08/1960</sdate>
    </born__date>
    <dni>95025187-C</dni>
    <email>joan.nebot@gmail.com</email>
    <movile>698497700</movile>
    <name>Joan</name>
    <lastname>Nebot Beltrán</lastname>
    <password>k9Z4Tpb2bWkblJ</password>
    <state>Online</state>
    <user>JoaNeb</user>
    <benefit>4413.0</benefit>
    <activity>2942</activity>
    <karma>high</karma>
  </RegU>
  <RegU>
    <age>47</age>
    <avataring>/home/osotemi/NetBeansProjects/Framework_v1.6.3/src/framework/img/profile_pictures/people-1.png</avataring>
    <born__date>
      <milsec>0</milsec>
      <second>0</second>
      <minute>0</minute>
      <hour>0</hour>
      <day>8</day>
      <month>7</month>
      <year>1968</year>
      <sdate>08/07/1968</sdate>
    </born__date>
    <dni>23603922-B</dni>
    <email>marc.sanz@gmail.com</email>
    <movile>640001075</movile>
    <name>Marc</name>
    <lastname>Sanz Serrano</lastname>
    <password>DI84A3oCmM</password>
    <state>Logged</state>
    <user>MarSan</user>
    <benefit>19854.0</benefit>
    <activity>13236</activity>
    <karma>high</karma>
  </RegU>
</list>